chemreps/__init__.py
chemreps/bag_of_bonds.py
chemreps/bagger.py
chemreps/bat.py
chemreps/coulomb_matrix.py
chemreps/dataset.py
chemreps/just_bonds.py
chemreps/data/qm9_bags.pkl
chemreps/utils/__init__.py
chemreps/utils/bag_handler.py
chemreps/utils/calcs.py
chemreps/utils/molecule.py
chemreps-0.1.0.dist-info/AUTHORS.md
chemreps-0.1.0.dist-info/LICENSE
chemreps-0.1.0.dist-info/METADATA
chemreps-0.1.0.dist-info/WHEEL
chemreps-0.1.0.dist-info/top_level.txt
chemreps-0.1.0.dist-info/RECORD
