Metadata-Version: 2.1
Name: chemreps
Version: 0.1.0
Summary: Molecular machine learning representations
Home-page: https://github.com/chemreps/chemreps
Maintainer: Dakota Folmsbee, Amanda Dumi, Shiv Upadhyay
Maintainer-email: dfolmsbee@gmail.com, amandaedumi@gmail.com, shivnupadhyay@gmail.com
License: MIT License
Platform: UNKNOWN
Classifier: Development Status :: 4 - Beta
Classifier: Intended Audience :: Science/Research
Classifier: Programming Language :: Python
Classifier: License :: OSI Approved :: MIT License
Classifier: Topic :: Scientific/Engineering :: Chemistry
Requires-Dist: cclib (>=1.5)
Requires-Dist: numpy (>=1.12)
